globus_search_cli/__init__.py
globus_search_cli/_sphinxext.py
globus_search_cli/config.py
globus_search_cli/printing.py
globus_search_cli/server_timing.py
globus_search_cli/version.py
globus_search_cli/commands/__init__.py
globus_search_cli/commands/delete_by_query.py
globus_search_cli/commands/ingest.py
globus_search_cli/commands/login.py
globus_search_cli/commands/logout.py
globus_search_cli/commands/query.py
globus_search_cli/commands/structured_query.py
globus_search_cli/commands/entry/__init__.py
globus_search_cli/commands/entry/create.py
globus_search_cli/commands/entry/delete.py
globus_search_cli/commands/entry/main.py
globus_search_cli/commands/entry/show.py
globus_search_cli/commands/entry/update.py
globus_search_cli/commands/index/__init__.py
globus_search_cli/commands/index/create.py
globus_search_cli/commands/index/list.py
globus_search_cli/commands/index/show.py
globus_search_cli/commands/index/role/__init__.py
globus_search_cli/commands/index/role/create.py
globus_search_cli/commands/index/role/delete.py
globus_search_cli/commands/index/role/list.py
globus_search_cli/commands/subject/__init__.py
globus_search_cli/commands/subject/delete.py
globus_search_cli/commands/subject/main.py
globus_search_cli/commands/subject/show.py
globus_search_cli/commands/task/__init__.py
globus_search_cli/commands/task/list.py
globus_search_cli/commands/task/main.py
globus_search_cli/commands/task/show.py
globus_search_cli/parsing/__init__.py
globus_search_cli/parsing/click_wrappers.py
globus_search_cli/parsing/main.py
globus_search_cli-0.8.2.dist-info/COPYING
globus_search_cli-0.8.2.dist-info/LICENSE
globus_search_cli-0.8.2.dist-info/METADATA
globus_search_cli-0.8.2.dist-info/WHEEL
globus_search_cli-0.8.2.dist-info/entry_points.txt
globus_search_cli-0.8.2.dist-info/top_level.txt
globus_search_cli-0.8.2.dist-info/RECORD
