Metadata-Version: 2.1
Name: globus-search-cli
Version: 0.8.2
Summary: Globus Search CLI
Home-page: https://github.com/globus/globus-search-cli
Author: Stephen Rosen
Author-email: sirosen@globus.org
Keywords: globus,cli,command line,search
Classifier: Development Status :: 7 - Inactive
Classifier: Intended Audience :: Developers
Classifier: License :: OSI Approved :: Apache Software License
Classifier: Operating System :: POSIX
Classifier: Programming Language :: Python
License-File: LICENSE
License-File: COPYING
Requires-Dist: click<9.0,>=8.0
Requires-Dist: globus-sdk<4,>=3.0.2
Requires-Dist: globus-sdk-tokenstorage==0.4.1
Provides-Extra: dev
Requires-Dist: pytest<5.0; extra == "dev"
Requires-Dist: pytest-cov<3.0; extra == "dev"
Requires-Dist: responses==0.14.0; extra == "dev"
Requires-Dist: pyyaml; extra == "dev"
